setup.py
blueCup/__init__.py
blueCup/celery.py
blueCup/conf.py
blueCup/task_base.py
blueCup/task_inner_platform.py
blueCup/task_notification.py
blueCup/task_xinyan.py
blueCup/third_interface_bill.py
blueCup.egg-info/PKG-INFO
blueCup.egg-info/SOURCES.txt
blueCup.egg-info/dependency_links.txt
blueCup.egg-info/requires.txt
blueCup.egg-info/top_level.txt
morn_bell/__init__.py
morn_bell/celery.py
morn_bell/conf_celery.py
morn_bell/third_interface_bill.py