Metadata-Version: 1.0
Name: blueCup
Version: 0.0.22
Summary: Little blue cup, who do not love?
Home-page: UNKNOWN
Author: UNKNOWN
Author-email: UNKNOWN
License: UNKNOWN
Platform: UNKNOWN
